face_identifier/__init__.py
face_identifier/face_comparation.py
face_identifier/face_detection.py
face_identifier/face_extraction.py
face_identifier/face_matching.py
face_identifier/face_vector_embedding.py
face_identifier-0.1.0a1.dist-info/METADATA
face_identifier-0.1.0a1.dist-info/WHEEL
face_identifier-0.1.0a1.dist-info/top_level.txt
face_identifier-0.1.0a1.dist-info/RECORD
